winrt/_winrt_windows_ui_xaml_controls.cp313-win_arm64.pyd
winrt/_winrt_windows_ui_xaml_controls.pyi
winrt/_winrt_windows_ui_xaml_controls_2.cp313-win_arm64.pyd
winrt/_winrt_windows_ui_xaml_controls_2.pyi
winrt/windows/ui/xaml/controls/__init__.py
winrt/windows/ui/xaml/controls/py.typed
winrt_windows_ui_xaml_controls-3.2.1.dist-info/METADATA
winrt_windows_ui_xaml_controls-3.2.1.dist-info/WHEEL
winrt_windows_ui_xaml_controls-3.2.1.dist-info/top_level.txt
winrt_windows_ui_xaml_controls-3.2.1.dist-info/RECORD
