Metadata-Version: 2.4
Name: winrt-Windows.UI.Xaml.Controls
Version: 3.2.1
Summary: Python projection of Windows Runtime (WinRT) APIs
License-Expression: MIT
Project-URL: Documentation, https://pywinrt.readthedocs.io
Project-URL: Repository, https://github.com/pywinrt/pywinrt
Project-URL: Changelog, https://github.com/pywinrt/pywinrt/blob/main/CHANGELOG.md
Classifier: Operating System :: Microsoft :: Windows
Classifier: Programming Language :: Python :: 3
Classifier: Programming Language :: Python :: Implementation :: CPython
Classifier: Intended Audience :: Developers
Requires-Python: >=3.9
Requires-Dist: winrt-runtime~=3.2.1.0
Requires-Dist: winrt-Windows.UI.Xaml~=3.2.1.0
Requires-Dist: winrt-Windows.UI.Xaml.Automation.Peers~=3.2.1.0
Requires-Dist: winrt-Windows.UI.Xaml.Controls.Primitives~=3.2.1.0
Requires-Dist: winrt-Windows.UI.Xaml.Media~=3.2.1.0
Provides-Extra: all
Requires-Dist: winrt-Windows.ApplicationModel.Contacts[all]~=3.2.1.0; extra == "all"
Requires-Dist: winrt-Windows.ApplicationModel.DataTransfer[all]~=3.2.1.0; extra == "all"
Requires-Dist: winrt-Windows.ApplicationModel.Search[all]~=3.2.1.0; extra == "all"
Requires-Dist: winrt-Windows.Foundation[all]~=3.2.1.0; extra == "all"
Requires-Dist: winrt-Windows.Foundation.Collections[all]~=3.2.1.0; extra == "all"
Requires-Dist: winrt-Windows.Globalization[all]~=3.2.1.0; extra == "all"
Requires-Dist: winrt-Windows.Media.Capture[all]~=3.2.1.0; extra == "all"
Requires-Dist: winrt-Windows.Media.Casting[all]~=3.2.1.0; extra == "all"
Requires-Dist: winrt-Windows.Media.Core[all]~=3.2.1.0; extra == "all"
Requires-Dist: winrt-Windows.Media.PlayTo[all]~=3.2.1.0; extra == "all"
Requires-Dist: winrt-Windows.Media.Playback[all]~=3.2.1.0; extra == "all"
Requires-Dist: winrt-Windows.Media.Protection[all]~=3.2.1.0; extra == "all"
Requires-Dist: winrt-Windows.Storage.Streams[all]~=3.2.1.0; extra == "all"
Requires-Dist: winrt-Windows.System[all]~=3.2.1.0; extra == "all"
Requires-Dist: winrt-Windows.UI[all]~=3.2.1.0; extra == "all"
Requires-Dist: winrt-Windows.UI.Composition[all]~=3.2.1.0; extra == "all"
Requires-Dist: winrt-Windows.UI.Core[all]~=3.2.1.0; extra == "all"
Requires-Dist: winrt-Windows.UI.Input.Inking[all]~=3.2.1.0; extra == "all"
Requires-Dist: winrt-Windows.UI.Text[all]~=3.2.1.0; extra == "all"
Requires-Dist: winrt-Windows.UI.Xaml[all]~=3.2.1.0; extra == "all"
Requires-Dist: winrt-Windows.UI.Xaml.Automation[all]~=3.2.1.0; extra == "all"
Requires-Dist: winrt-Windows.UI.Xaml.Automation.Peers[all]~=3.2.1.0; extra == "all"
Requires-Dist: winrt-Windows.UI.Xaml.Controls.Primitives[all]~=3.2.1.0; extra == "all"
Requires-Dist: winrt-Windows.UI.Xaml.Data[all]~=3.2.1.0; extra == "all"
Requires-Dist: winrt-Windows.UI.Xaml.Documents[all]~=3.2.1.0; extra == "all"
Requires-Dist: winrt-Windows.UI.Xaml.Input[all]~=3.2.1.0; extra == "all"
Requires-Dist: winrt-Windows.UI.Xaml.Interop[all]~=3.2.1.0; extra == "all"
Requires-Dist: winrt-Windows.UI.Xaml.Media[all]~=3.2.1.0; extra == "all"
Requires-Dist: winrt-Windows.UI.Xaml.Media.Animation[all]~=3.2.1.0; extra == "all"
Requires-Dist: winrt-Windows.UI.Xaml.Navigation[all]~=3.2.1.0; extra == "all"
Requires-Dist: winrt-Windows.Web[all]~=3.2.1.0; extra == "all"
Requires-Dist: winrt-Windows.Web.Http[all]~=3.2.1.0; extra == "all"
